app/__init__.py
app/manage.py
app/demo/__init__.py
app/demo/settings.py
app/demo/urls.py
app/demo/wsgi.py
app/demo/countries/__init__.py
app/demo/countries/admin.py
app/demo/countries/apps.py
app/demo/countries/choices.py
app/demo/countries/models.py
app/demo/countries/translation.py
app/demo/countries/urls.py
app/demo/countries/views.py
app/demo/countries/management/__init__.py
app/demo/countries/management/commands/__init__.py
app/demo/countries/management/commands/wait_for_db.py
app/demo/countries/migrations/0001_initial.py
app/demo/countries/migrations/0002_createsuperuser.py
app/demo/countries/migrations/0003_country_is_safe.py
app/demo/countries/migrations/0004_country_created.py
app/demo/countries/migrations/0005_country_modified.py
app/demo/countries/migrations/0006_country_time.py
app/demo/countries/migrations/0007_person.py
app/demo/countries/migrations/0008_auto_20190625_0816.py
app/demo/countries/migrations/0009_auto_20190702_2042.py
app/demo/countries/migrations/0010_person_date.py
app/demo/countries/migrations/0011_person_description.py
app/demo/countries/migrations/0012_auto_20190710_0913.py
app/demo/countries/migrations/0013_proxyperson.py
app/demo/countries/migrations/0014_auto_20190719_1032.py
app/demo/countries/migrations/0015_auto_20190719_1539.py
app/demo/countries/migrations/0016_person_smart.py
app/demo/countries/migrations/0017_country1_country2_country3_country4_country5_country6.py
app/demo/countries/migrations/0018_person_time.py
app/demo/countries/migrations/0019_auto_20200127_2043.py
app/demo/countries/migrations/0020_auto_20200713_1630.py
app/demo/countries/migrations/0021_alter_country_options.py
app/demo/countries/migrations/__init__.py
app/demo/documents/__init__.py
app/demo/documents/admin.py
app/demo/documents/apps.py
app/demo/documents/forms.py
app/demo/documents/models.py
app/demo/documents/migrations/0001_initial.py
app/demo/documents/migrations/0002_auto_20190719_1539.py
app/demo/documents/migrations/0003_link.py
django_material_admin_plus-1.8.14.dist-info/LICENCE
django_material_admin_plus-1.8.14.dist-info/LICENCE.TXT
django_material_admin_plus-1.8.14.dist-info/METADATA
django_material_admin_plus-1.8.14.dist-info/WHEEL
django_material_admin_plus-1.8.14.dist-info/top_level.txt
django_material_admin_plus-1.8.14.dist-info/RECORD
