Metadata-Version: 2.1
Name: django-material-admin-plus
Version: 1.8.14
Summary: Material Design For Django Administration
Home-page: https://github.com/tho-asterist/django-material-admin
Author: Anton Maistrenko
Author-email: it2015maistrenko@gmail.com
Maintainer: ActRecipe Team
Maintainer-email: actrecipe-dev@actrecipe.com
License: MIT License
Classifier: Programming Language :: Python :: 3.7
Classifier: Programming Language :: Python :: 3.8
Classifier: Programming Language :: Python :: 3.9
Classifier: Programming Language :: Python :: 3.10
Classifier: Programming Language :: Python :: 3.11
Classifier: Programming Language :: Python :: 3.12
Classifier: Framework :: Django :: 3.2
Classifier: Framework :: Django :: 4.2
Classifier: License :: OSI Approved :: MIT License
Classifier: Operating System :: OS Independent
License-File: LICENCE
License-File: LICENCE.TXT
